caniform/Extend.py
caniform/__init__.py
caniform-0.0.10.dist-info/LICENSE
caniform-0.0.10.dist-info/METADATA
caniform-0.0.10.dist-info/WHEEL
caniform-0.0.10.dist-info/top_level.txt
caniform-0.0.10.dist-info/RECORD
