Metadata-Version: 2.1
Name: caniform
Version: 0.0.10
Summary: A package that extends the functionality of Pandas.
Home-page: https://gitlab.com/tomathon/caniform/
Author: tomathon
Author-email: tomathon.dev@pm.me
Project-URL: Bug Tracker, https://gitlab.com/tomathon/caniform/-/issues/
Classifier: Programming Language :: Python :: 3
Classifier: License :: OSI Approved :: MIT License
Classifier: Operating System :: OS Independent
Requires-Python: >=3.6
License-File: LICENSE
